pnnx/__init__.py
pnnx/pnnx
pnnx/utils/__init__.py
pnnx/utils/convert.py
pnnx/utils/export.py
pnnx/utils/utils.py
pnnx-20251119.dist-info/METADATA
pnnx-20251119.dist-info/WHEEL
pnnx-20251119.dist-info/entry_points.txt
pnnx-20251119.dist-info/top_level.txt
pnnx-20251119.dist-info/RECORD
